[{"name":"","author":"","category":"","count":0},{"name":"","author":"","category":"","count":0},{"name":"","author":"","category":"","count":0},{"name":"","author":"","category":"","count":0},{"name":"","author":"","category":"","count":0},{"name":"完美世界","author":"辰东","category":"玄幻","count":4670735},{"name":"大主宰","author":"天蚕土豆","category":"玄幻","count":2030568},{"name":"莽荒纪","author":"我吃西红柿","category":"仙侠","count":1605278},{"name":"神级英雄","author":"大烟缸","category":"游戏","count":1413007},{"name":"悍戚","author":"庚新","category":"历史","count":1189892},{"name":"圣堂","author":"骷髅精灵","category":"仙侠","count":1090631},{"name":"凡人修仙传","author":"忘语","category":"仙侠","count":1077547},{"name":"最强弃少","author":"鹅是老五","category":"都市","count":928260},{"name":"宝鉴","author":"打眼","category":"都市","count":921193},{"name":"调教香江","author":"王梓钧","category":"都市","count":915630},{"name":"花都十二钗","author":"傲无常","category":"都市","count":823111},{"name":"斗罗大陆II绝世唐门","author":"唐家三少","category":"玄幻","count":781543},{"name":"暴力牛魔王","author":"泰平绅士","category":"奇幻","count":627414},{"name":"灵域","author":"逆苍天","category":"玄幻","count":542972},{"name":"唐砖","author":"孑与2","category":"历史","count":533925},{"name":"电影世界冒险记","author":"九道光","category":"科幻","count":532245},{"name":"医道官途","author":"石章鱼","category":"都市","count":523256},{"name":"傲世九重天","author":"风凌天下","category":"玄幻","count":497968},{"name":"大道独行","author":"雾外江山","category":"仙侠","count":455291},{"name":"降临在电影世界","author":"四海123456","category":"科幻","count":455113},{"name":"求魔","author":"耳根","category":"仙侠","count":451104},{"name":"我的法宝是电脑","author":"陈怡然","category":"仙侠","count":450772},{"name":"奥术神座","author":"爱潜水的乌贼","category":"玄幻","count":428628},{"name":"重生之超级战舰","author":"彩虹之门","category":"科幻","count":423905},{"name":"校花的贴身高手","author":"鱼人二代","category":"都市","count":415208},{"name":"我的女友是丧尸","author":"黑暗荔枝","category":"科幻","count":412631},{"name":"全职高手","author":"蝴蝶蓝","category":"游戏","count":403329},{"name":"绝对权力","author":"不信天上掉...","category":"都市","count":400264},{"name":"金庸绝学异世横行","author":"御剑斋","category":"玄幻","count":399342},{"name":"妙手玄医","author":"炖肉大锅菜","category":"都市","count":396768},{"name":"大唐第一庄","author":"晨风天堂","category":"历史","count":372020},{"name":"无限之地球人的逆袭","author":"干煸鱿鱼须","category":"科幻","count":368705},{"name":"赘婿","author":"愤怒的香蕉","category":"历史","count":366582},{"name":"死神推销员","author":"黄金米","category":"都市","count":359018},{"name":"斗破苍穹之无上之境","author":"夜雨闻铃0","category":"同人","count":353432},{"name":"天龙里的剑客","author":"寻幽问胜","category":"武侠","count":351994},{"name":"网游之零纪元","author":"不是浮云","category":"游戏","count":345924},{"name":"青云门徒","author":"破军少帅","category":"仙侠","count":343729},{"name":"我有一个小世界","author":"迷路行者","category":"仙侠","count":343445},{"name":"草根富豪","author":"零青城","category":"都市","count":327261},{"name":"捡宝","author":"三疯妖孽","category":"都市","count":326940},{"name":"九星天辰诀","author":"发飙的蜗牛","category":"玄幻","count":322848},{"name":"斗破苍穹","author":"天蚕土豆","category":"玄幻","count":316614},{"name":"胜者为王","author":"林海听涛","category":"竞技","count":315493},{"name":"香港风云娱乐","author":"小楼明夜","category":"都市","count":314134},{"name":"风云之傲绝","author":"樱海猫猫","category":"武侠","count":308726},{"name":"房术","author":"跑盘","category":"都市","count":307532},{"name":"光明纪元","author":"血红","category":"玄幻","count":299015},{"name":"外星继承人","author":"唐小水","category":"都市","count":297729},{"name":"醉枕江山","author":"月关","category":"历史","count":291399},{"name":"巨虫尸巫","author":"竹上猪猪","category":"玄幻","count":289159},{"name":"黑暗血时代","author":"天下飘火","category":"科幻","count":288937},{"name":"龙珠之绫叶传奇","author":"永恒炽天使","category":"同人","count":274917},{"name":"异界之机关大师","author":"吞吞史莱姆","category":"玄幻","count":273870},{"name":"汉末暴徒","author":"风卷尘生","category":"历史","count":271919},{"name":"风流医圣","author":"蔡晋","category":"都市","count":270419},{"name":"梦起武侠世界","author":"悲秋寒蜩","category":"游戏","count":268536},{"name":"暴力前锋","author":"华晓鸥","category":"竞技","count":264345},{"name":"超级符警","author":"九城","category":"都市","count":254734},{"name":"神秘之旅","author":"滚开","category":"奇幻","count":253479},{"name":"武动乾坤","author":"天蚕土豆","category":"玄幻","count":253049},{"name":"奇门赘婿","author":"邻家小六","category":"都市","count":251560},{"name":"无限之倾世妖孽","author":"轻国大帝","category":"科幻","count":250124},{"name":"末世重生之龙帝","author":"天不负01","category":"科幻","count":248694},{"name":"将夜","author":"猫腻","category":"玄幻","count":248330},{"name":"修真教授生活录","author":"纵马昆仑","category":"都市","count":246275},{"name":"武极天下","author":"蚕茧里的牛","category":"玄幻","count":244888},{"name":"末世盗贼行","author":"雨水","category":"科幻","count":243640},{"name":"萌娘武侠世界","author":"三十二变","category":"游戏","count":243622},{"name":"无敌天下","author":"神见","category":"玄幻","count":241576},{"name":"超级武学系统","author":"龍歾","category":"都市","count":239511},{"name":"警衣卫","author":"鼎天ing","category":"都市","count":239297},{"name":"极品鉴宝师","author":"古栋","category":"都市","count":238670},{"name":"抗日之兵魂传说","author":"丑牛1985","category":"军事","count":235820},{"name":"超脑武神","author":"阳光照耀的...","category":"玄幻","count":235614},{"name":"我是幸存者","author":"型男密码","category":"科幻","count":233793},{"name":"从金庸武侠开始","author":"追星HZY","category":"游戏","count":233668},{"name":"超级星际战士","author":"我叫排云掌","category":"科幻","count":233518},{"name":"匪风悍气","author":"醛石","category":"都市","count":230269},{"name":"剑道独尊","author":"剑游太虚","category":"玄幻","count":229902},{"name":"新官","author":"皮诺草","category":"都市","count":228020},{"name":"剑动九天","author":"孤单地飞","category":"玄幻","count":227733},{"name":"锻仙","author":"新兵扛老枪","category":"仙侠","count":226312},{"name":"游侠系统","author":"西楚中原","category":"玄幻","count":225914},{"name":"洪荒之君临九天","author":"乌龟看王八","category":"仙侠","count":223013},{"name":"夜宋","author":"格子里的阳光","category":"历史","count":222598},{"name":"娱乐圈之极品大明星","author":"逆天成神记","category":"都市","count":222563},{"name":"花都酒剑仙","author":"千里大黑马","category":"都市","count":222109},{"name":"死亡乐园","author":"十二饭叔","category":"游戏","count":219628},{"name":"官人很忙","author":"半卖半送","category":"历史","count":219508},{"name":"武神空间","author":"傅啸尘","category":"玄幻","count":217084},{"name":"超级文明之主宰","author":"陆大雄","category":"科幻","count":216387},{"name":"极品天骄","author":"风少羽","category":"都市","count":215879},{"name":"越战的血","author":"远征士兵","category":"军事","count":214976},{"name":"都市透心术","author":"青云之路无...","category":"都市","count":214287},{"name":"醉枕香江","author":"忧郁的青蛙","category":"都市","count":213223},{"name":"红色仕途","author":"鸿蒙树","category":"都市","count":212020},{"name":"官值","author":"攀公","category":"都市","count":210857},{"name":"都市大厨仙","author":"雪中黑袍","category":"都市","count":210854},{"name":"都市之最强纨绔","author":"左耳思念","category":"都市","count":210373},{"name":"","author":"","category":"","count":0},{"name":"","author":"","category":"","count":0},{"name":"","author":"","category":"","count":0},{"name":"","author":"","category":"","count":0},{"name":"","author":"","category":"","count":0},{"name":"","author":"","category":"","count":0},{"name":"","author":"","category":"","count":0},{"name":"","author":"","category":"","count":0},{"name":"","author":"","category":"","count":0},{"name":"混在抗战","author":"古龙岗","category":"历史","count":210031},{"name":"系统特工","author":"浅唱忧郁","category":"都市","count":209099},{"name":"无上巫法","author":"大巫师","category":"玄幻","count":207648},{"name":"特级乡村生活","author":"水天风","category":"都市","count":207271},{"name":"洪荒之儒圣","author":"桃源闲人","category":"仙侠","count":204958},{"name":"天骄无双","author":"跳舞","category":"玄幻","count":202473},{"name":"女优养成","author":"倚楼独语","category":"都市","count":201150},{"name":"遮天","author":"辰东","category":"仙侠","count":200775},{"name":"北乔峰","author":"不老年华","category":"武侠","count":200557},{"name":"超级杂货店","author":"叫我小样","category":"都市","count":198352},{"name":"斗罗大陆","author":"唐家三少","category":"玄幻","count":198109},{"name":"帝尊","author":"宅猪","category":"仙侠","count":197666},{"name":"灾厄降临","author":"黑十三郎","category":"科幻","count":196959},{"name":"七星创世录","author":"笑竹天","category":"仙侠","count":196707},{"name":"官财","author":"冷狂人","category":"都市","count":196560},{"name":"霸清","author":"绝谷刀客","category":"历史","count":196351},{"name":"奉系江山","author":"青史尽成灰","category":"历史","count":193612},{"name":"大圣传","author":"说梦者","category":"仙侠","count":193371},{"name":"盘龙","author":"我吃西红柿","category":"奇幻","count":192178},{"name":"末世修真系统","author":"邵公子","category":"科幻","count":189706},{"name":"带藏獒入洪荒","author":"浮流西元","category":"仙侠","count":189283},{"name":"官道无疆","author":"瑞根","category":"都市","count":188644},{"name":"荒神","author":"洪荒未名","category":"仙侠","count":187951},{"name":"末法王座","author":"庄毕凡","category":"玄幻","count":187713},{"name":"夜寰","author":"守着猫睡觉...","category":"仙侠","count":187421},{"name":"纨绔仙医","author":"步征","category":"都市","count":187128},{"name":"法师驾到","author":"睡到十三点","category":"游戏","count":186992},{"name":"龙珠之新生赛亚人","author":"凌风青龙","category":"同人","count":185952},{"name":"官高一级","author":"书虫大大","category":"都市","count":185905},{"name":"重生超级帝国","author":"末日游侠","category":"历史","count":185570},{"name":"封神大仙","author":"聪明强","category":"仙侠","count":181837},{"name":"重生之我的书记人生","author":"宝石猫","category":"都市","count":181048},{"name":"蛮尊","author":"斯文猫叔","category":"玄幻","count":180821},{"name":"天赋无双","author":"邀明日","category":"游戏","count":180451},{"name":"狂蟒之灾","author":"霸恶","category":"科幻","count":180408},{"name":"我叫布里茨","author":"机器人布里茨","category":"游戏","count":178196},{"name":"黑铁之堡","author":"醉虎","category":"科幻","count":177928},{"name":"仙侠农场","author":"蓝色雨夜","category":"仙侠","count":177687},{"name":"首席御医","author":"银河九天","category":"都市","count":176271},{"name":"海贼王之无证名医","author":"并不知道的...","category":"同人","count":174020},{"name":"母巢王虫","author":"刘奉常","category":"科幻","count":169935},{"name":"鉴宝天书","author":"维果","category":"都市","count":169062},{"name":"无限作死","author":"虎皮猫大人","category":"科幻","count":167911},{"name":"洪荒青莲","author":"浮流西元","category":"仙侠","count":167699},{"name":"士子风流","author":"上山打老虎额","category":"历史","count":166519},{"name":"封神绝仙","author":"小唱天下白","category":"玄幻","count":165947},{"name":"朝元","author":"温酒煮花生","category":"仙侠","count":165218},{"name":"带着英雄无敌闯异界","author":"不死滴鸟人","category":"玄幻","count":164300},{"name":"龙使养成计划","author":"兵库北番长","category":"玄幻","count":164204},{"name":"抗战之最强民兵","author":"步枪打蚊子","category":"军事","count":163121},{"name":"大唐暴力宅男","author":"宅男也是男","category":"历史","count":162918},{"name":"修真民工","author":"叶狂徒","category":"都市","count":162854},{"name":"不朽圣尊","author":"傲月长空","category":"玄幻","count":162790},{"name":"武者在洪荒","author":"超级高手","category":"仙侠","count":161211},{"name":"动漫热","author":"妖娆血花","category":"科幻","count":161067},{"name":"官仙","author":"陈风笑","category":"都市","count":160955},{"name":"终极黑暗大反派","author":"黑暗LOLI","category":"科幻","count":160949},{"name":"潜规则教皇","author":"码字小苹果","category":"都市","count":159809},{"name":"超能转化","author":"松柏君","category":"都市","count":159704},{"name":"无敌打印机","author":"冷月寒杀","category":"历史","count":158675},{"name":"最终救赎","author":"诸生浮屠","category":"科幻","count":158387},{"name":"华山气宗的形意宗师","author":"杀胡儿","category":"武侠","count":158139},{"name":"无限之美剧空间","author":"野山黑猪","category":"科幻","count":158068},{"name":"一柱倾天","author":"雷之牙","category":"都市","count":154306},{"name":"地狱电影院","author":"黑色火种","category":"灵异","count":154006},{"name":"山村桃源记","author":"习之墨","category":"都市","count":151598},{"name":"牧周","author":"天净沙秋思","category":"历史","count":151510},{"name":"大导演","author":"西瓜子的父亲","category":"都市","count":150321},{"name":"我是木匠皇帝","author":"独坐池塘","category":"历史","count":149861},{"name":"重生之超级强国","author":"牧场星辰","category":"都市","count":149598},{"name":"极品修真邪少","author":"面红耳赤","category":"仙侠","count":148058},{"name":"公子留仙","author":"泛东流","category":"仙侠","count":147513},{"name":"奋斗在武侠世界","author":"可爱红烧肉","category":"游戏","count":147489},{"name":"随身悠闲乡村生活","author":"民窑","category":"都市","count":147078},{"name":"我的元首","author":"落爷孤独","category":"历史","count":146501},{"name":"晚唐","author":"木子蓝色","category":"历史","count":146172},{"name":"天才相师","author":"打眼","category":"都市","count":145485},{"name":"超级制造系统","author":"月逸清辉","category":"都市","count":144192},{"name":"警神","author":"静夜寄思","category":"都市","count":143996},{"name":"旷世神相","author":"九世探花","category":"都市","count":143823},{"name":"我的民国生涯","author":"千斤顶","category":"历史","count":143499},{"name":"漫画家之梦","author":"断罪蝴蝶","category":"都市","count":142732},{"name":"悠然神农","author":"小风大人","category":"都市","count":142399},{"name":"网游之剑走偏锋","author":"黑乎乎的老妖","category":"游戏","count":141848},{"name":"校长放开我","author":"校长蹦跳跳","category":"都市","count":141785},{"name":"型月的七曜魔法使","author":"冷月天权","category":"同人","count":141666},{"name":"超级散仙II","author":"那一抹绯色","category":"都市","count":141373},{"name":"都市至尊天骄","author":"我丑到灵魂...","category":"都市","count":141137},{"name":"独医无二","author":"笑论语","category":"都市","count":140317},{"name":"超级位面交易终端","author":"黄刑","category":"都市","count":139629},{"name":"诱香蛊皇","author":"虎躯常震","category":"仙侠","count":138767},{"name":"吞噬星空","author":"我吃西红柿","category":"科幻","count":138586},{"name":"升邪","author":"豆子惹的祸","category":"仙侠","count":137920},{"name":"世家","author":"千年静守","category":"都市","count":137431},{"name":"拣宝","author":"烛","category":"都市","count":136611},{"name":"三国第一强兵","author":"鲈州鱼","category":"历史","count":136066},{"name":"超级电影","author":"难想","category":"都市","count":135635},{"name":"黑暗猎杀场","author":"不意马","category":"科幻","count":135223},{"name":"三国将星系统","author":"天光破凌云","category":"游戏","count":135077},{"name":"灌篮之我是良田","author":"青涩的柑橘","category":"同人","count":134968},{"name":"","author":"","category":"","count":0},{"name":"","author":"","category":"","count":0},{"name":"","author":"","category":"","count":0},{"name":"","author":"","category":"","count":0},{"name":"","author":"","category":"","count":0},{"name":"","author":"","category":"","count":0},{"name":"","author":"","category":"","count":0},{"name":"","author":"","category":"","count":0},{"name":"","author":"","category":"","count":0},{"name":"武极巅峰","author":"雨辰宇","category":"玄幻","count":134882},{"name":"漫游收藏家","author":"笔墨轮回","category":"同人","count":134706},{"name":"空间基地军火商","author":"低端疯子","category":"都市","count":134685},{"name":"忍者世界的近战大师","author":"路过的陆仁贾","category":"同人","count":134198},{"name":"斗破之魂族帝师","author":"三角四方圈...","category":"同人","count":134078},{"name":"美梦时代","author":"俊秀才","category":"都市","count":132815},{"name":"一切从葫芦娃开始","author":"三月严寒","category":"仙侠","count":132114},{"name":"功夫帝皇","author":"老驴东来","category":"都市","count":130895},{"name":"拿无限当单机","author":"不带电","category":"科幻","count":130179},{"name":"重生为山","author":"一目尽天涯","category":"仙侠","count":130013},{"name":"杨康的幸福生活","author":"越空","category":"武侠","count":128940},{"name":"大魔能时代","author":"三谢","category":"科幻","count":128536},{"name":"封神之余元","author":"临朝","category":"仙侠","count":128531},{"name":"我是汉灵帝","author":"不做亡国君","category":"历史","count":128462},{"name":"数据修炼系统","author":"独翼客","category":"游戏","count":127912},{"name":"农夫三国","author":"苍山虎","category":"历史","count":127801},{"name":"怪厨","author":"田十","category":"都市","count":126953},{"name":"位面无良奸商","author":"高帅不富","category":"都市","count":126946},{"name":"树宗","author":"祖树","category":"科幻","count":126807},{"name":"诸天祭","author":"乘风御剑","category":"玄幻","count":126674},{"name":"笑傲之武侠系统","author":"飞雪连天射...","category":"游戏","count":126281},{"name":"百炼成仙","author":"幻雨","category":"仙侠","count":126044},{"name":"杀神","author":"逆苍天","category":"玄幻","count":125936},{"name":"抗战虎贲","author":"秋风起叶落","category":"军事","count":125698},{"name":"问题妹妹恋上我","author":"负是非","category":"都市","count":125052},{"name":"权财","author":"尝谕","category":"都市","count":124701},{"name":"处女座的旅途","author":"参云子道长","category":"同人","count":124367},{"name":"剑逆苍穹","author":"EK巧克力","category":"玄幻","count":124094},{"name":"绝品天医","author":"叶天南","category":"都市","count":123251},{"name":"无限阵营","author":"林青衣03","category":"科幻","count":123101},{"name":"学霸也要谈恋爱","author":"学霸殿下","category":"同人","count":122460},{"name":"晚明","author":"柯山梦","category":"历史","count":122330},{"name":"超级游戏商城","author":"抓不住风的雨","category":"玄幻","count":122232},{"name":"极品装备制造师","author":"雪夜如墨","category":"游戏","count":122176},{"name":"我和系统是好友","author":"酒剑九九","category":"游戏","count":122095},{"name":"都市重生高手","author":"一片楼月","category":"都市","count":121722},{"name":"茅山笔记","author":"钱二翘","category":"灵异","count":121458},{"name":"官术","author":"狗狍子","category":"都市","count":120823},{"name":"神农传承者之位面诊所","author":"暴力快递员","category":"都市","count":120703},{"name":"重生之调教娱乐圈","author":"有梦之人","category":"都市","count":120456},{"name":"红色警戒之民国","author":"华丽的虚伪","category":"历史","count":119784},{"name":"盛唐入侵中世纪","author":"骑士王和夏亚","category":"历史","count":119508},{"name":"强者来临","author":"云中古城","category":"都市","count":119075},{"name":"无上妖君","author":"听风画秋雨","category":"仙侠","count":117797},{"name":"武炼巅峰","author":"莫默","category":"玄幻","count":117782},{"name":"星球重生","author":"伊修塔","category":"科幻","count":117650},{"name":"狂神","author":"唐家三少","category":"玄幻","count":116101},{"name":"隐杀","author":"愤怒的香蕉","category":"都市","count":116020},{"name":"全能戒指","author":"最无聊4","category":"都市","count":115929},{"name":"大海王","author":"燃烧的黑火","category":"玄幻","count":115840},{"name":"青冥天","author":"銘渊","category":"玄幻","count":114963},{"name":"民国第一军阀","author":"落雨流痕","category":"历史","count":114519},{"name":"超级位面掏宝商","author":"冰块儿","category":"都市","count":114365},{"name":"明朝伪君子","author":"贼眉鼠眼","category":"历史","count":114132},{"name":"兽王三国","author":"小菜送上","category":"历史","count":114027},{"name":"武侠世界男儿行","author":"我吃唐三藏","category":"游戏","count":113905},{"name":"神座","author":"皇甫奇","category":"玄幻","count":113741},{"name":"游戏与综漫的旅程","author":"海王波士顿","category":"同人","count":113735},{"name":"全职穿越","author":"BUFF全开","category":"科幻","count":113624},{"name":"网游之大玄幻","author":"易亦易","category":"游戏","count":113107},{"name":"天下无职","author":"单纯宅男","category":"游戏","count":112456},{"name":"星耀娱乐圈","author":"晕血的羔羊","category":"都市","count":112296},{"name":"洪荒通天之截教风云","author":"无味鸭梨","category":"仙侠","count":112046},{"name":"神墓","author":"辰东","category":"玄幻","count":111996},{"name":"玄幻位面大冒险","author":"幻道逍遥","category":"游戏","count":111102},{"name":"猎美之王","author":"天魔圣","category":"都市","count":110161},{"name":"仙门大道","author":"武阁","category":"仙侠","count":109998},{"name":"极品空间农场","author":"虎口男","category":"都市","count":109648},{"name":"花都捕王","author":"逗妇花","category":"都市","count":109555},{"name":"重生世界首富","author":"薛庄十三","category":"都市","count":109278},{"name":"逍遥房东","author":"永恒火","category":"都市","count":108977},{"name":"三国之妖才","author":"历史跳跃的...","category":"历史","count":108598},{"name":"钓鳌客","author":"天侑明","category":"仙侠","count":108277},{"name":"仙逆","author":"耳根","category":"仙侠","count":108214},{"name":"百草空间","author":"左右指尖","category":"都市","count":108165},{"name":"巫族至尊","author":"清风傲阳","category":"仙侠","count":107873},{"name":"人皇","author":"十步行","category":"玄幻","count":107411},{"name":"神武八荒","author":"一颗","category":"玄幻","count":107375},{"name":"韩娱之天王","author":"呓语痴人","category":"都市","count":106766},{"name":"一号传奇","author":"听雨水寒","category":"竞技","count":106714},{"name":"最终信念","author":"逺辰","category":"科幻","count":106519},{"name":"火影之完美世界","author":"我正减肥中","category":"同人","count":105920},{"name":"自由的巫妖","author":"海伦因","category":"奇幻","count":105607},{"name":"步步封疆","author":"南闲","category":"都市","count":105571},{"name":"对不起我迷路了","author":"黄天也死了","category":"同人","count":105524},{"name":"大腕崛起","author":"泥白佛","category":"都市","count":105358},{"name":"官道之1976","author":"想见江南","category":"都市","count":104751},{"name":"大器宗","author":"不问苍生问...","category":"仙侠","count":103520},{"name":"我的神明与教廷","author":"妖梦使十御","category":"游戏","count":103181},{"name":"神捕乱宋","author":"理查德唐僧","category":"历史","count":103158},{"name":"从零开始","author":"雷云风暴","category":"游戏","count":103121},{"name":"修神外传","author":"小段探花","category":"仙侠","count":102296},{"name":"三国之暴君颜良","author":"陷阵都尉","category":"历史","count":102197},{"name":"惊悚乐园","author":"三天两觉","category":"游戏","count":101300},{"name":"史上最牛召唤","author":"那一抹绯红","category":"玄幻","count":101211},{"name":"娱乐圈之超级巨星","author":"财神加身","category":"都市","count":101123},{"name":"郭嘉","author":"一念长空","category":"历史","count":100872},{"name":"超级当铺系统","author":"如烟浮云","category":"都市","count":100649},{"name":"黄金遁","author":"冰火阑珊","category":"都市","count":100118},{"name":"姑苏南慕容","author":"找一个角落","category":"武侠","count":99818},{"name":"","author":"","category":"","count":0},{"name":"","author":"","category":"","count":0},{"name":"","author":"","category":"","count":0},{"name":"","author":"","category":"","count":0},{"name":"","author":"","category":"","count":0},{"name":"","author":"","category":"","count":0},{"name":"","author":"","category":"","count":0},{"name":"","author":"","category":"","count":0},{"name":"","author":"","category":"","count":0},{"name":"夺鼎1617","author":"猛将如云","category":"历史","count":99723},{"name":"异世之娱乐巨星","author":"贵妃凉皮","category":"都市","count":99663},{"name":"极品乡村生活","author":"名窑","category":"都市","count":99445},{"name":"网游之超级国宝","author":"love小七","category":"游戏","count":99200},{"name":"重生之抽奖空间","author":"逍遥随鑫","category":"都市","count":99047},{"name":"超级能源强国","author":"志鸟村","category":"都市","count":98375},{"name":"手机里面有异界","author":"雪落书窗","category":"都市","count":98176},{"name":"骨尊","author":"汉隶","category":"仙侠","count":97785},{"name":"无限之武侠轮回世界","author":"翼V龙","category":"游戏","count":97728},{"name":"斩仙","author":"任怨","category":"仙侠","count":96823},{"name":"大明官","author":"随轻风去","category":"历史","count":95921},{"name":"傲天狂尊","author":"乌山云雨","category":"玄幻","count":95916},{"name":"穿越归来","author":"梦道者","category":"都市","count":95753},{"name":"都市大供奉","author":"闹挺","category":"仙侠","count":95685},{"name":"传奇控卫","author":"小艾神","category":"竞技","count":95472},{"name":"龙骑战机","author":"华表","category":"科幻","count":95440},{"name":"黑客","author":"青幕山","category":"都市","count":95306},{"name":"异世邪君","author":"风凌天下","category":"玄幻","count":95151},{"name":"全球黑暗期","author":"轻浮烟尘","category":"科幻","count":95052},{"name":"战神领主","author":"木牛流猫","category":"游戏","count":94879},{"name":"超级无线网","author":"小伙儿伤不起","category":"都市","count":94314},{"name":"官德","author":"奥比椰","category":"都市","count":94243},{"name":"诸神之师","author":"摇光Aliciz...","category":"玄幻","count":93670},{"name":"首长","author":"夏言冰","category":"都市","count":93558},{"name":"未来职业者","author":"藏7锋","category":"都市","count":93124},{"name":"疯狂太岁","author":"最爱吃凉糕","category":"都市","count":92815},{"name":"无限龙神","author":"霓虹灯泡","category":"科幻","count":91923},{"name":"极品大小老婆","author":"大光明","category":"都市","count":91511},{"name":"再世香港梦","author":"跳刀阿七","category":"都市","count":91299},{"name":"全职家丁","author":"蓝领笑笑生","category":"玄幻","count":90944},{"name":"全能奇才","author":"九指仙尊","category":"都市","count":90394},{"name":"天龙之祸害武林","author":"天空一只鱼","category":"武侠","count":89537},{"name":"无限之李帅西传奇","author":"两仪熙","category":"科幻","count":89380},{"name":"大灵王","author":"鱼楽","category":"仙侠","count":88665},{"name":"重生游戏洪荒世界之证帝","author":"牛顿也吃苹...","category":"仙侠","count":88301},{"name":"四象记","author":"君子无醉","category":"仙侠","count":88240},{"name":"不死不灭","author":"辰东","category":"武侠","count":88060},{"name":"重生之绝世天骄","author":"怕冷的火焰","category":"都市","count":87654},{"name":"真理天文","author":"仙之琉璃","category":"同人","count":87473},{"name":"掏宝王","author":"有一眼","category":"都市","count":87352},{"name":"那无限的世界","author":"baka梦云","category":"同人","count":87043},{"name":"源动星辰","author":"天穹小猫01","category":"科幻","count":86671},{"name":"恐慌沸腾","author":"相思洗红豆","category":"科幻","count":86644},{"name":"末日超级游戏系统","author":"沐日海洋","category":"科幻","count":86617},{"name":"武侠世界大冒险","author":"五方行尽","category":"游戏","count":86041},{"name":"天地霸气诀","author":"我丑到灵魂...","category":"玄幻","count":85980},{"name":"网游之无敌圣骑","author":"海说","category":"游戏","count":85586},{"name":"西游之重生六耳","author":"武阳道人","category":"仙侠","count":85527},{"name":"全能闲人","author":"光暗之心","category":"都市","count":85058},{"name":"洪荒之广成子","author":"左中郎将","category":"仙侠","count":85022},{"name":"随身桃源空间","author":"慵懒的雨","category":"都市","count":84965},{"name":"升帝","author":"竹管","category":"玄幻","count":84943},{"name":"知北游","author":"洛水","category":"仙侠","count":84941},{"name":"天尊重生","author":"神见","category":"玄幻","count":84704},{"name":"大生化时代","author":"落寞痴人","category":"科幻","count":84631},{"name":"凶鸟猎食图谱","author":"接口卡","category":"玄幻","count":84612},{"name":"智能王","author":"无量大大","category":"都市","count":84403},{"name":"女神试用期","author":"我是男神","category":"都市","count":84027},{"name":"剑气冲霄","author":"冷落霜","category":"玄幻","count":83995},{"name":"极品美女帝国","author":"蓝豆生南国","category":"都市","count":83949},{"name":"重生民国之中华崛起","author":"574981","category":"军事","count":83827},{"name":"云中子异界游","author":"李圣人","category":"玄幻","count":83699},{"name":"穿越者纵横动漫世界","author":"龙之宫","category":"同人","count":83665},{"name":"阳神","author":"梦入神机","category":"仙侠","count":83365},{"name":"人不要脸则无敌","author":"阿福","category":"都市","count":83287},{"name":"鬼行三国","author":"浮光浅如梦","category":"历史","count":83249},{"name":"网游之奥术至高","author":"鬼影行者","category":"游戏","count":83217},{"name":"重生天龙之虚竹","author":"东郭梦鱼","category":"武侠","count":83216},{"name":"极品巫医","author":"夜也荒唐","category":"都市","count":82909},{"name":"一树擎天","author":"乘云驾鹤","category":"仙侠","count":82762},{"name":"山村生活任逍遥","author":"光芒万丈","category":"都市","count":82616},{"name":"邪恶契约","author":"一川烟草S","category":"游戏","count":82561},{"name":"英雄无敌之召唤千军","author":"游戏苦手","category":"游戏","count":82298},{"name":"抗日之铁血军魂","author":"长风","category":"军事","count":82157},{"name":"位面开拓者","author":"温柔","category":"科幻","count":82021},{"name":"至尊仙皇","author":"流连往返1979","category":"玄幻","count":81893},{"name":"超级明星制作人","author":"浪拍云","category":"都市","count":81893},{"name":"霸蜀","author":"庄不周","category":"历史","count":81791},{"name":"仙海道迹","author":"坤水丈人","category":"仙侠","count":81626},{"name":"黄金瞳","author":"打眼","category":"都市","count":81551},{"name":"空间传送","author":"古夜凡","category":"都市","count":81526},{"name":"天元神诀","author":"大观山人","category":"仙侠","count":81203},{"name":"纸醉江山","author":"巡洋舰","category":"历史","count":81168},{"name":"魔界的女婿","author":"点精灵","category":"玄幻","count":80972},{"name":"官妖","author":"青云之路无...","category":"都市","count":80796},{"name":"花月楼","author":"醒来时的孤独","category":"武侠","count":80575},{"name":"穿越令狐冲","author":"小胖子上山","category":"武侠","count":80564},{"name":"神印王座","author":"唐家三少","category":"玄幻","count":80358},{"name":"惊门","author":"徐公子胜治","category":"都市","count":80183},{"name":"超级工业帝国","author":"雪漂","category":"历史","count":80178},{"name":"超时空犯罪集团","author":"尖叫酒杯","category":"科幻","count":80113},{"name":"重生之洪荒上古天庭","author":"珞璎","category":"仙侠","count":80061},{"name":"善良的死神","author":"唐家三少","category":"奇幻","count":79569},{"name":"中华第四帝国","author":"流泪的鱼wyj","category":"历史","count":79345},{"name":"天赋武侠系统","author":"寂寞埋藏","category":"游戏","count":79309},{"name":"民国枭雄","author":"断刃天涯","category":"历史","count":79303},{"name":"洪荒祖巫烛九阴传","author":"小小妖道","category":"仙侠","count":78500},{"name":"英雄监狱","author":"黄华溢","category":"游戏","count":78480},{"name":"仙府道途","author":"云鹤真人","category":"仙侠","count":78211},{"name":"笑傲之我为教主狂","author":"萧天郎","category":"武侠","count":77842},{"name":"","author":"","category":"","count":0},{"name":"","author":"","category":"","count":0},{"name":"","author":"","category":"","count":0},{"name":"","author":"","category":"","count":0},{"name":"","author":"","category":"","count":0},{"name":"","author":"","category":"","count":0},{"name":"","author":"","category":"","count":0},{"name":"","author":"","category":"","count":0},{"name":"","author":"","category":"","count":0},{"name":"死人经","author":"冰临神下","category":"武侠","count":77734},{"name":"醉卧花都","author":"火华木南","category":"都市","count":77720},{"name":"宠魅","author":"鱼的天空","category":"玄幻","count":77569},{"name":"辛亥大英雄","author":"河马散人","category":"历史","count":77507},{"name":"火影之大科学家","author":"前兆领袖","category":"同人","count":77460},{"name":"无限英灵战姬","author":"草尖上的云雀","category":"科幻","count":77362},{"name":"武侠变","author":"云白天蓝","category":"游戏","count":77047},{"name":"末世之三妻四妾","author":"我爱狐仙","category":"科幻","count":76924},{"name":"满唐春","author":"炮兵","category":"历史","count":76814},{"name":"植祖","author":"我就是龙","category":"玄幻","count":76530},{"name":"最终进化","author":"卷土","category":"科幻","count":76397},{"name":"星虐","author":"潇疯","category":"玄幻","count":76319},{"name":"洪荒之无量剑尊","author":"贫道你猜啊","category":"仙侠","count":76098},{"name":"重生之王语嫣","author":"中箭的膝盖","category":"仙侠","count":76023},{"name":"剑道独神","author":"六道沉沦","category":"玄幻","count":75978},{"name":"功高权重","author":"老井古柳","category":"都市","count":75861},{"name":"剑起神雕","author":"燕青灵","category":"同人","count":75753},{"name":"综漫之幻想萝莉","author":"无奈试试","category":"同人","count":75688},{"name":"无尽丹田","author":"横扫天涯","category":"玄幻","count":75374},{"name":"罚神之剑","author":"玉雪阳","category":"仙侠","count":75361},{"name":"王棋游戏","author":"啪啪桑","category":"玄幻","count":75217},{"name":"无限武侠新世界","author":"三江水","category":"游戏","count":75180},{"name":"道行","author":"鹤舟","category":"仙侠","count":75070},{"name":"强者禁区","author":"左右言它","category":"都市","count":75006},{"name":"暗黑之火法","author":"浮标","category":"游戏","count":74955},{"name":"超级神兽养殖大师","author":"没落的游吟...","category":"玄幻","count":74924},{"name":"邪神传说","author":"云天空","category":"玄幻","count":74717},{"name":"凡人同人之仙界篇","author":"坏坏2002","category":"同人","count":74388},{"name":"裁决","author":"七十二编","category":"玄幻","count":73867},{"name":"迷失在地球的外星综合舰","author":"冷雪冰川","category":"都市","count":73679},{"name":"铁血抗战918","author":"寒冬三月","category":"军事","count":73526},{"name":"超级百宝囊","author":"开心小帅","category":"玄幻","count":73499},{"name":"鸿蒙炼神道","author":"缘星空","category":"仙侠","count":73389},{"name":"极品家丁","author":"禹岩","category":"历史","count":73225},{"name":"无限众神游戏","author":"迷茫的蛇","category":"科幻","count":73222},{"name":"重生寻宝","author":"噩梦格式化","category":"都市","count":73184},{"name":"武宰","author":"松家大少","category":"玄幻","count":73030},{"name":"北宋末年当神棍","author":"雪满林中","category":"仙侠","count":72895},{"name":"圣渎","author":"烤到七分熟","category":"奇幻","count":72713},{"name":"网游之我是海贼王","author":"灰色下雨天","category":"游戏","count":72659},{"name":"超级战兵","author":"一丝不苟","category":"都市","count":72522},{"name":"无限归来之超级警察","author":"勿明","category":"都市","count":72364},{"name":"兽性猛士","author":"侠飞","category":"军事","count":72315},{"name":"合体双修","author":"我是墨水","category":"仙侠","count":72281},{"name":"十二骷髅","author":"炎楠","category":"灵异","count":71511},{"name":"大家都来打鬼子","author":"活着就","category":"军事","count":71331},{"name":"无限之军事基地","author":"西方蜘蛛","category":"历史","count":71223},{"name":"蛋王","author":"蒙古小哒子","category":"都市","count":71217},{"name":"重生为星","author":"吃书虫虫","category":"仙侠","count":71205},{"name":"娱乐篮坛","author":"赵孽啊","category":"竞技","count":71123},{"name":"仙壶农庄","author":"狂奔的海马","category":"都市","count":71099},{"name":"随身山河图","author":"山村户口","category":"都市","count":70821},{"name":"天龙之乔峰纵横天下","author":"笑一笑十年...","category":"武侠","count":70759},{"name":"唯我网王","author":"醉武天下VS...","category":"同人","count":70717},{"name":"无限之角色扮演","author":"悲伤的但丁","category":"科幻","count":70498},{"name":"绝命诱惑","author":"心梦无痕","category":"都市","count":70451},{"name":"九千岁","author":"半世峥嵘","category":"历史","count":70260},{"name":"笑傲江湖之华山风云","author":"爱情拾荒者","category":"同人","count":70237},{"name":"明末边军一小兵","author":"老白牛","category":"历史","count":69937},{"name":"都市之神显","author":"望冰心","category":"都市","count":69902},{"name":"饲主","author":"王少少","category":"都市","count":69822},{"name":"地球上唯一的魔法师","author":"奥巴牛总统","category":"都市","count":69625},{"name":"众星之主","author":"一伤二十八","category":"仙侠","count":69510},{"name":"阐教第一妖","author":"熊猫不会唱歌","category":"仙侠","count":69359},{"name":"活人禁地","author":"o鬼若o","category":"灵异","count":69136},{"name":"最后人类","author":"黑瞳王","category":"玄幻","count":69136},{"name":"魔兽世界之野猪人崛起","author":"朱头人","category":"游戏","count":69118},{"name":"宠物小精灵之流清","author":"冰火星精灵","category":"同人","count":69059},{"name":"随身海场空间","author":"不是楚飞","category":"都市","count":68962},{"name":"海贼王之法师传奇","author":"护舒宝之怒","category":"同人","count":68940},{"name":"生化末世的幸福生活","author":"在南方的毛豆","category":"科幻","count":68759},{"name":"洪荒之冥河寻道","author":"利叉草","category":"仙侠","count":68570},{"name":"天才丹师","author":"胡赖","category":"都市","count":68475},{"name":"美女如云之国际闲人","author":"跃千愁","category":"都市","count":68376},{"name":"韩娱霸者","author":"允木果","category":"都市","count":68242},{"name":"我家后院是异界","author":"深海孔雀","category":"都市","count":68237},{"name":"三国好谋士","author":"香烟本草","category":"历史","count":68230},{"name":"重铸江山","author":"绝世皇风","category":"历史","count":68176},{"name":"百炼焚仙","author":"如履","category":"仙侠","count":67914},{"name":"末世游戏场","author":"三斤大米","category":"科幻","count":67903},{"name":"希灵帝国","author":"远瞳","category":"科幻","count":67440},{"name":"狙击南宋","author":"寇十五郎","category":"历史","count":67307},{"name":"重生封神之我为哪吒","author":"枯树倚藤","category":"仙侠","count":67253},{"name":"无敌升级王","author":"可爱内内","category":"玄幻","count":67131},{"name":"灭世魔藤","author":"刃上S","category":"仙侠","count":67031},{"name":"人神","author":"南朝陈","category":"仙侠","count":66999},{"name":"国军悍将","author":"江湖老鸟","category":"历史","count":66762},{"name":"洪荒造化","author":"w风雪","category":"仙侠","count":66712},{"name":"虫神暴君","author":"九指匹夫","category":"科幻","count":66637},{"name":"抗战之红色警戒","author":"大刀老猿","category":"历史","count":66538},{"name":"酒神","author":"唐家三少","category":"奇幻","count":66382},{"name":"江湖大反派","author":"寒暑不知年","category":"游戏","count":66351},{"name":"王朝教父","author":"临河羡鱼翁","category":"竞技","count":66299},{"name":"都市版英雄无敌","author":"猛虎道长","category":"都市","count":66077},{"name":"官路弯弯","author":"拾寒阶","category":"都市","count":66025},{"name":"官策","author":"寂寞读南华","category":"都市","count":65846},{"name":"口袋妖怪之逆袭","author":"裂壳的鸡蛋","category":"同人","count":65600},{"name":"不朽冥河","author":"血武残阳","category":"仙侠","count":65521},{"name":"超级神警","author":"六划先生","category":"都市","count":65399},{"name":"大花贼","author":"星长云","category":"玄幻","count":65109},{"name":"","author":"","category":"","count":0},{"name":"","author":"","category":"","count":0},{"name":"","author":"","category":"","count":0},{"name":"","author":"","category":"","count":0}]